rishab/feed_data.py
rishab/map_reduce.py
rishab/server.py
rishab/test.py
rishab-0.0.1.dist-info/METADATA
rishab-0.0.1.dist-info/RECORD
rishab-0.0.1.dist-info/WHEEL
rishab-0.0.1.dist-info/entry_points.txt
rishab-0.0.1.dist-info/top_level.txt
