Metadata-Version: 2.1
Name: rishab
Version: 0.0.1
Summary: A library to auto construct DL Models using an API service
Home-page: https://github.com/rishab-sharma/rishab.git
Author: Rishab Sharma
Author-email: rishabsharmaddn@gmail.com
License: MIT
Platform: UNKNOWN
Classifier: Development Status :: 4 - Beta
Classifier: Intended Audience :: System Administrators
Classifier: License :: OSI Approved :: Apache Software License
Classifier: Programming Language :: Python :: 2
Requires-Dist: keras (>=2.1.2)
Requires-Dist: flask (>=0.12)
